COPYRIGHT.txt
CURRENT_PACKAGE_NAME
CURRENT_VERSION
LICENSE.txt
MANIFEST.in
README.rst
caerp_setup.json
dev_requirements.txt
endi_setup.json
moogli-erp_setup.json
pyproject.toml
requirements.txt
setup.py
caerp/__init__.py
caerp/celery.log
caerp/default_layouts.py
caerp/exception.py
caerp/interfaces.py
caerp/log.py
caerp/pshell.py
caerp/resources.py
caerp/sql.log
caerp/.pytest_cache/.gitignore
caerp/.pytest_cache/CACHEDIR.TAG
caerp/.pytest_cache/README.md
caerp/.pytest_cache/v/cache/stepwise
caerp/alembic/README
caerp/alembic/__init__.py
caerp/alembic/env.py
caerp/alembic/exceptions.py
caerp/alembic/script.py.mako
caerp/alembic/utils.py
caerp/alembic/versions/1_0_432d76e49a9c.py
caerp/alembic/versions/1_1_3ffdda6a6fe6.py
caerp/alembic/versions/1_2_1f548f8115e8.py
caerp/alembic/versions/1_3_1902ba0cc2ac.py
caerp/alembic/versions/1_4_2cc9251fb0bb.py
caerp/alembic/versions/1_4_adding_polymorphic_i_3f52b6b0ed7c.py
caerp/alembic/versions/1_4_ajout_du_statusperso_41116dd5c5c8.py
caerp/alembic/versions/1_4_fiche_client_1dce987687aa.py
caerp/alembic/versions/1_4_migration_des_factur_14b76f64614c.py
caerp/alembic/versions/1_4_migration_du_code_cl_209c0f6d7620.py
caerp/alembic/versions/1_4_renommage_des_colonn_1e7d7781a47b.py
caerp/alembic/versions/1_4_taux_de_tva_par_1987a6d83e5f.py
caerp/alembic/versions/1_5_address_field_on_23fd141c9484.py
caerp/alembic/versions/1_5_champ_adresse_mu_70853b5576c.py
caerp/alembic/versions/1_5_migrating_expens_362fc5306d54.py
caerp/alembic/versions/1_5_migrating_financ_4a4eba558244.py
caerp/alembic/versions/1_5_migrating_paymen_1f07ae132ac8.py
caerp/alembic/versions/1_5_migrating_work_u_1212f113f03b.py
caerp/alembic/versions/1_5_moving_manualinv_2a7a5275c441.py
caerp/alembic/versions/1_5_multiple_client__1cc9ff114346.py
caerp/alembic/versions/1_6_migrate_code_com_29299007fe7d.py
caerp/alembic/versions/1_7_active_tag_2b29f533fdfc.py
caerp/alembic/versions/1_7_add_compte_cg_to_4ce6b915de98.py
endi.egg-info/PKG-INFO
endi.egg-info/SOURCES.txt
endi.egg-info/dependency_links.txt
endi.egg-info/entry_points.txt
endi.egg-info/not-zip-safe
endi.egg-info/requires.txt
endi.egg-info/top_level.txt