Metadata-Version: 2.2
Name: endi
Version: 2026.1.3
Summary: Progiciel de gestion pour CAE
Home-page: https://framagit.org/caerp/caerp
Author: Coopérer pour entreprendre
Author-email: contact@cooperer.coop
Keywords: pyramid,business,web
Classifier: License :: OSI Approved :: GNU General Public License v3 (GPLv3)
Classifier: Programming Language :: Python
Classifier: Framework :: Pyramid
Classifier: Topic :: Internet :: WWW/HTTP
Classifier: Topic :: Internet :: WWW/HTTP :: WSGI :: Application
Requires-Python: >=3.7
License-File: LICENSE.txt
Requires-Dist: alembic==1.13.1
Requires-Dist: Beaker==1.13.0
Requires-Dist: Chameleon==3.9.0
Requires-Dist: colander==2.0
Requires-Dist: ColanderAlchemy
Requires-Dist: Cython
Requires-Dist: deform==2.0.14
Requires-Dist: deform_extensions==0.9
Requires-Dist: docopt==0.5.0
Requires-Dist: caerp_payment==2024.0.11
Requires-Dist: caerp_sign_pdf==2024.2.2
Requires-Dist: factur-x==2.3
Requires-Dist: fanstatic==1.1
Requires-Dist: filedepot==0.10.0
Requires-Dist: httpagentparser==1.9.5
Requires-Dist: nh3==0.2.14
Requires-Dist: html5lib==1.1
Requires-Dist: setuptools==75.8.2
Requires-Dist: ipython
Requires-Dist: js.bootstrap==3.3.1
Requires-Dist: js.chosen==0.9.14
Requires-Dist: js.deform==2.0.14
Requires-Dist: js.jquery==1.9.1
Requires-Dist: js.jquery-form==3.09
Requires-Dist: js.jquery-maskedinput==1.3.1
Requires-Dist: js.jquery-maskmoney==3.0.2
Requires-Dist: js.jquery_sortable==0.9.12
Requires-Dist: js.jquery-timepicker-addon==1.3-1
Requires-Dist: js.jqueryui==1.10.3
Requires-Dist: js.tinymce==4.1.5
Requires-Dist: Mako==1.3.0
Requires-Dist: mysqlclient==2.2.7
Requires-Dist: openpyxl==3.1.2
Requires-Dist: PasteDeploy==3.1.0
Requires-Dist: peppercorn==0.6
Requires-Dist: pillow==11.3.0
Requires-Dist: pi-heif==1.1.1
Requires-Dist: plaster-pastedeploy==1.0.1
Requires-Dist: paginate==0.5.6
Requires-Dist: paginate-sqlalchemy==0.3.1
Requires-Dist: py3o.template==0.10.0
Requires-Dist: pyjwkest==1.3.6
Requires-Dist: pyparsing==3.0.9
Requires-Dist: pyramid==2.0.2
Requires-Dist: pyramid-beaker==0.8
Requires-Dist: pyramid-chameleon==0.3
Requires-Dist: pyramid-deform==0.2
Requires-Dist: pyramid_exclog==1.0
Requires-Dist: pyramid_ipython
Requires-Dist: pyramid-layout==1.0
Requires-Dist: pyramid-mailer==0.15.1
Requires-Dist: pyramid-mako==1.1.0
Requires-Dist: pyramid-methodrewrite==0.2.3
Requires-Dist: pyramid_services==2.2
Requires-Dist: pyramid-tm==2.5
Requires-Dist: pyramid_retry==2.1.1
Requires-Dist: pyramid_session_redis
Requires-Dist: requests==2.32.3
Requires-Dist: pydyf==0.11.0
Requires-Dist: reportlab==4.0.8
Requires-Dist: repoze.lru==0.6
Requires-Dist: requests==2.32.3
Requires-Dist: simplejson==3.3.1
Requires-Dist: sqla_inspect==0.9.1
Requires-Dist: SQLAlchemy==1.4.50
Requires-Dist: transaction==4.0
Requires-Dist: translationstring==1.2
Requires-Dist: typing_extensions
Requires-Dist: Unidecode==0.04.17
Requires-Dist: venusian==3.1.0
Requires-Dist: waitress==2.1.2
Requires-Dist: WebHelpers2==2.1
Requires-Dist: WebOb==1.8.9
Requires-Dist: zope.component==7.0
Requires-Dist: zope.deprecation==5.0
Requires-Dist: zope.event==6.0
Requires-Dist: zope.interface==8.0.1
Requires-Dist: zope.sqlalchemy==4.0
Requires-Dist: odfpy==1.4.1
Requires-Dist: pyexcel-io==0.6.6
Requires-Dist: WeasyPrint==66.0
Requires-Dist: pyvat==1.3.17
Requires-Dist: schwifty==2025.1.0
Requires-Dist: python-stdnum==2.1
Requires-Dist: pyramid-celery==4.0.0
Requires-Dist: redis
Requires-Dist: sylk_parser==0.5
Requires-Dist: celery==5.4.0
Provides-Extra: dev
Requires-Dist: ipdb==0.13.4; extra == "dev"
Requires-Dist: libsass==0.20.1; extra == "dev"
Requires-Dist: pyramid_debugtoolbar; extra == "dev"
Requires-Dist: black==22.3.0; extra == "dev"
Requires-Dist: flake8; extra == "dev"
Requires-Dist: boussole==2.0; extra == "dev"
Requires-Dist: pytest<7.0,>=6.0.2; extra == "dev"
Requires-Dist: freezegun<1.1,>=1.0.0; extra == "dev"
Requires-Dist: Faker<5.0,>=4.1.3; extra == "dev"
Requires-Dist: WebTest<2.1,>=2.0.35; extra == "dev"
Requires-Dist: pre-commit; extra == "dev"
Dynamic: author
Dynamic: author-email
Dynamic: classifier
Dynamic: description
Dynamic: description-content-type
Dynamic: home-page
Dynamic: keywords
Dynamic: provides-extra
Dynamic: requires-dist
Dynamic: requires-python
Dynamic: summary
